{
  "total_violations": 3,
  "compliance_score": 88.46153846153845,
  "timestamp": "2025-08-17 11:24:28",
  "violations_by_type": {
    "file_size": 3
  },
  "violations": [
    {
      "file_path": "app\\ingestion\\page.tsx",
      "violation_type": "file_size",
      "severity": "high",
      "line_number": null,
      "function_name": null,
      "actual_value": 572,
      "expected_value": 300,
      "description": "File exceeds 300 line limit",
      "fix_suggestion": "Split into 2 modules"
    },
    {
      "file_path": "app\\enterprise-demo\\enhanced-page.tsx",
      "violation_type": "file_size",
      "severity": "high",
      "line_number": null,
      "function_name": null,
      "actual_value": 455,
      "expected_value": 300,
      "description": "File exceeds 300 line limit",
      "fix_suggestion": "Split into 2 modules"
    },
    {
      "file_path": "app\\demo\\page.tsx",
      "violation_type": "file_size",
      "severity": "high",
      "line_number": null,
      "function_name": null,
      "actual_value": 356,
      "expected_value": 300,
      "description": "File exceeds 300 line limit",
      "fix_suggestion": "Split into 2 modules"
    }
  ],
  "summary": {
    "total_files_checked": 26,
    "files_with_violations": 3,
    "max_file_lines": 300,
    "max_function_lines": 8,
    "compliance_score": 88.46153846153845
  },
  "category_scores": {
    "real_system": {
      "violations": 3,
      "files_with_violations": 3,
      "total_files": 26,
      "score": 88.46153846153845
    },
    "test_files": {
      "violations": 0,
      "files_with_violations": 0,
      "total_files": 0,
      "score": 100.0
    },
    "other": {
      "violations": 0,
      "files_with_violations": 0,
      "total_files": 0,
      "score": 100.0
    }
  }
}