{
  "instances": [
    {
      "command": "/gitcommitgardener",
      "name": "git-commit-gardener",
      "description": "Maintains git commit hygiene and standards",
      "allowed_tools": ["Task", "Read", "Glob", "Grep", "Write", "Edit", "MultiEdit", "Bash"],
      "permission_mode": "acceptEdits",
      "output_format": "stream-json",
      "session_id": null,
      "clear_history": true,
      "compact_history": false,
      "pre_commands": [
        "/clear"
      ]
    },
    {
      "command": "/gitissueprogressorv2",
      "name": "git-issue-progressor-v2",
      "description": "Advances GitHub issues through workflow states",
      "allowed_tools": ["Task", "Read", "Glob", "Grep", "Write", "Edit", "MultiEdit", "Bash"],
      "permission_mode": "acceptEdits",
      "output_format": "stream-json",
      "session_id": null,
      "clear_history": true,
      "compact_history": false,
      "pre_commands": [
        "/clear"
      ]
    },
    {
      "command": "/gitissueprogressorv3",
      "name": "git-issue-progressor-v3",
      "description": "Advanced GitHub issue workflow management",
      "allowed_tools": ["Task", "Read", "Glob", "Grep", "Write", "Edit", "MultiEdit", "Bash"],
      "permission_mode": "acceptEdits",
      "output_format": "stream-json",
      "session_id": null,
      "clear_history": true,
      "compact_history": false,
      "pre_commands": [
        "/clear"
      ]
    },
    {
      "command": "/gitissueplannerv1",
      "name": "git-issue-planner-v1",
      "description": "Plans and structures GitHub issue resolution",
      "allowed_tools": ["Task", "Read", "Glob", "Grep", "Write", "Edit", "MultiEdit", "Bash"],
      "permission_mode": "acceptEdits",
      "output_format": "stream-json",
      "session_id": null,
      "clear_history": true,
      "compact_history": false,
      "pre_commands": [
        "/clear"
      ]
    },
    {
      "command": "/prmergergit",
      "name": "pr-merger-git",
      "description": "Handles pull request merging workflows",
      "allowed_tools": ["Task", "Read", "Glob", "Grep", "Write", "Edit", "MultiEdit", "Bash"],
      "permission_mode": "acceptEdits",
      "output_format": "stream-json",
      "session_id": null,
      "clear_history": true,
      "compact_history": false,
      "pre_commands": [
        "/clear"
      ]
    }
  ]
}